BasicWires/4Wires/4Wire.v
module FourWre (
    input a, b, c,
    output w, x, y, z 
);

    assign w = a;
    assign x = b;
    assign y = b;
    assign z = c;

endmodule

BasicWires/4Wires/TB1.v
`timescale 1ns / 1ps

module TB1;

reg a, b, c;
wire w, x, y, z;

FourWre dut (
    .a(a),
    .b(b),
    .c(c),
    .w(w),
    .x(x),
    .y(y),
    .z(z)
);

    initial begin 
        $dumpfile("dump.vcd");
        $dumpvars(0, TB1);

        a = 1'b0; b = 1'b0; c = 1'b0; #10;
        a = 1'b0; b = 1'b0; c = 1'b1; #10;
        a = 1'b0; b = 1'b1; c = 1'b0; #10;
        a = 1'b1; b = 1'b0; c = 1'b0; #10;
        a = 1'b0; b = 1'b1; c = 1'b1; #10;
        a = 1'b1; b = 1'b1; c = 1'b0; #10;
        a = 1'b1; b = 1'b0; c = 1'b1; #10;
        a = 1'b1; b = 1'b1; c = 1'b1; #10;
        

        $finish;
    end
endmodule

BasicWires/4Wires/dump.vcd
$date
	Wed Jul 22 19:25:09 2026
$end
$version
	Icarus Verilog
$end
$timescale
	1ps
$end
$scope module TB1 $end
$var wire 1 ! z $end
$var wire 1 " y $end
$var wire 1 # x $end
$var wire 1 $ w $end
$var reg 1 % a $end
$var reg 1 & b $end
$var reg 1 ' c $end
$scope module dut $end
$var wire 1 % a $end
$var wire 1 & b $end
$var wire 1 ' c $end
$var wire 1 $ w $end
$var wire 1 # x $end
$var wire 1 " y $end
$var wire 1 ! z $end
$upscope $end
$upscope $end
$enddefinitions $end
$comment Show the parameter values. $end
$dumpall
$end
#0
$dumpvars
0'
0&
0%
0$
0#
0"
0!
$end
#10000
1!
1'
#20000
0!
0'
1#
1"
1&
#30000
0#
0"
0&
1$
1%
#40000
1!
1'
1#
1"
1&
0$
0%
#50000
0!
0'
1$
1%
#60000
1!
1'
0#
0"
0&
#70000
1#
1"
1&
